udp_proxy_server/__init__.py
udp_proxy_server/cli.py
udp_proxy_server/udpconverter.py
udp_proxy_server-0.0.2.dist-info/LICENSE
udp_proxy_server-0.0.2.dist-info/METADATA
udp_proxy_server-0.0.2.dist-info/WHEEL
udp_proxy_server-0.0.2.dist-info/entry_points.txt
udp_proxy_server-0.0.2.dist-info/top_level.txt
udp_proxy_server-0.0.2.dist-info/RECORD
