Metadata-Version: 2.1
Name: udp-proxy-server
Version: 0.0.2
Summary: udp proxy server to intercept udp
Home-page: https://github.com/manfred-kaiser/udp-proxy-server
Author: Manfred Kaiser
Author-email: manfred.kaiser@logfile.at
License: UNKNOWN
Platform: UNKNOWN
Classifier: Programming Language :: Python :: 3
Classifier: License :: OSI Approved :: GNU General Public License v3 (GPLv3)
Classifier: Topic :: System :: Networking
Requires-Python: >= 3.5
Requires-Dist: enhancements
